{"Alabaster Exarch":{"hashedName":"TuinxL","checksum":"UG/r","artworks":[{"id":"7c7b4c53-2f2b-49df-a6bf-37f29b9e5746","index":"3","hash":"mObgG"},{"id":"db52578b-cf61-4cc6-b730-21e3bd1752ce","index":"3","hash":"Cq1Gf"}]},"Avenging Force":{"hashedName":"ZZZJhx","checksum":"GUjy","artworks":[{"id":"22993c97-4c0e-4b20-b61e-0765854b1d0c","index":"2","hash":"9rDRA"}]},"Baby Lamassu":{"hashedName":"ntcS24","checksum":"xRcn","artworks":[{"id":"b1e88fda-7d3b-4302-b0b0-4eee0012e193","index":"1","hash":"BKXza"}]},"Blackmarble Gargoyle":{"hashedName":"HES5VP","checksum":"BG4f","artworks":[{"id":"a408d92c-6e6e-4d30-93ad-e526a5c9555f","index":"3","hash":"8n44h"}]},"Chronosand Sphinx":{"hashedName":"dwha4D","checksum":"gupB","artworks":[{"id":"8c6c5803-34bd-4238-bf4b-5436f269949d","index":"3","hash":"FmkTO"}]},"Cryptosphinx":{"hashedName":"XrrsRe","checksum":"R1k6","artworks":[{"id":"250e747b-c7e8-4a5b-a483-65446cd307aa","index":"2","hash":"2wV5S"}]},"Damaged Automaton":{"hashedName":"3lRkwb","checksum":"M6c5","artworks":[{"id":"3644d9f4-a154-4538-96ea-489d6da10cda","index":"2","hash":"D3H5n"}]},"Diviner of Fates":{"hashedName":"i8mgjm","checksum":"VGCs","artworks":[{"id":"9b1cd3ba-f0fb-43df-a5df-aa0555f184e0","index":"0","hash":"Av5Zj"},{"id":"7e6524d5-fc47-4a64-ac87-5ec5a5ddad4c","index":"1","hash":"7OaXc"},{"id":"7e6524d5-fc47-4a64-ac87-5ec5a5ddad4c","index":"3","hash":"EhFwL"}]},"Doma Angel":{"hashedName":"DoigNK","checksum":"jfkp","artworks":[{"id":"e10bf9b3-3d4a-458c-b4e9-595c4cddd9bf","index":"0","hash":"/2p3e"},{"id":"bf2b9797-ca47-418b-8b51-f73b166d794e","index":"0","hash":"pV0jK"}]},"Dove of Serenity":{"hashedName":"zHbYd9","checksum":"ya1d","artworks":[{"id":"bd138556-f391-44ec-ab68-5aa4b5a9f606","index":"1","hash":"DUX/D"}]},"Dream Traveler":{"hashedName":"QnR0qA","checksum":"XIAM","artworks":[{"id":"1ae58892-c0c7-4cd2-b4f2-61e436a76acb","index":"0","hash":"n7B72"}]},"Embalmed Apophis":{"hashedName":"8IqRNy","checksum":"63pA","artworks":[{"id":"13499ec2-9a5a-4595-9ccd-fbcfe0fffeaf","index":"0","hash":"r8bTi"}]},"Feline Ushabti":{"hashedName":"iPWho9","checksum":"Qu/H","artworks":[{"id":"7b73514c-612c-4f7a-b7b0-8d03ff687646","index":"1","hash":"t8ZyG"}]},"Guardian of the Gates":{"hashedName":"8O5rqu","checksum":"TPTh","artworks":[{"id":"13533eea-4c56-4787-a8d1-5b5de4d2fe40","index":"0","hash":"Ilkww"}]},"Hallowed Exorcist":{"hashedName":"3UYffW","checksum":"+Duy","artworks":[{"id":"fb9ad282-f768-4726-b79b-f40c11d0277b","index":"3","hash":"TK6xQ"}]},"Harmonic Echo":{"hashedName":"ORQbOv","checksum":"8/mH","artworks":[{"id":"2fb88f6b-7b37-40f3-9ddf-e46da64b9024","index":"2","hash":"eGnjj"}]},"Ibis Ushabti":{"hashedName":"q9E5LE","checksum":"LAUH","artworks":[{"id":"10569df3-af61-474e-9997-08b1211eac4b","index":"3","hash":"5xR16"}]},"Maze Master Sphinx":{"hashedName":"X/8dGo","checksum":"PyBm","artworks":[{"id":"9ccceaff-97a6-4625-9bea-6567b85c04ef","index":"0","hash":"mallS"}]},"Mystic Puzzle Box":{"hashedName":"YcXOeP","checksum":"Mfgr","artworks":[{"id":"0cf0be47-c57f-4feb-84e6-1790219ba54b","index":"0","hash":"+Mni6"}]},"Oasis Sprite":{"hashedName":"I/6Hwy","checksum":"ieSf","artworks":[{"id":"16fb7678-58aa-43f4-976c-6411d373341c","index":"1","hash":"JS6hq"}]},"Pharaoh's Bodyguard":{"hashedName":"qQhdBy","checksum":"rKpz","artworks":[{"id":"4e1424fd-a4dd-430d-b5db-da68488eb78a","index":"0","hash":"bwrPS"}]},"Scripture Monkey":{"hashedName":"ZvcJcB","checksum":"9D8L","artworks":[{"id":"3321903a-a303-44ee-8b5d-3487bd693fa9","index":"3","hash":"X332q"}]},"Sekhem Chariot":{"hashedName":"3CEeZ7","checksum":"Nap6","artworks":[{"id":"a6b9796b-edf3-4af3-9ed5-c8182508947e","index":"1","hash":"Z/PrK"}]},"Obsidian Scarab":{"hashedName":"cBwVvG","checksum":"pNvc","artworks":[{"id":"5742c34c-4780-42a9-88f6-56a1b9ce53f4","index":"0","hash":"RMOji"},{"id":"8b38cf8f-f197-4c3a-befd-e184edaf89b1","index":"1","hash":"76oRz"},{"id":"05eda290-6a12-4283-8598-0203ce13dc18","index":"0","hash":"J3PfB"},{"id":"355d3553-313f-4638-bf69-02b34f653fae","index":"2","hash":"w/0hj"},{"id":"3be1dd1a-b5e1-4576-84ea-2c53a6c076e3","index":"1","hash":"VEAMk"}]},"Thunderswarm Skirmisher":{"hashedName":"bK658h","checksum":"vMhT","artworks":[{"id":"1352ae1c-e93b-4eeb-9c2b-8d45efc47f38","index":"0","hash":"tKOqX"},{"id":"e58d0ede-21d0-4b9c-87b3-4745b329f97d","index":"0","hash":"Q3S57"}]},"Tranquil Herd Gem Titan":{"hashedName":"RyuDAn","checksum":"cpEl","artworks":[{"id":"ed7547f6-59f6-4674-8e51-448f70e1a062","index":"1","hash":"FDeZm"}]},"Thunderswarm Pegasus":{"hashedName":"aIIUZf","checksum":"k8/b","artworks":[{"id":"2892cac4-ecfc-4b4f-a4e9-1eb61a4971a8","index":"3","hash":"IB5Pr"}]},"Wrath of the Pharaoh":{"hashedName":"fxHxI8","checksum":"tYJo","artworks":[{"id":"557ea44c-dc30-4519-93c0-96caf2f97815","index":"3","hash":"PLOy7"}]},"Crimson Flamechick":{"hashedName":"EMxaSp","checksum":"EZ1O","artworks":[{"id":"0867635b-b993-4e89-adc9-840fac5e98ae","index":"2","hash":"Yja8L"}]},"Thunderswarm Celestial":{"hashedName":"Ea3Aho","checksum":"tUPY","artworks":[{"id":"496903ec-9e29-4e96-baed-fbc1c72e67a2","index":"3","hash":"bNstr"}]},"The Second Wing":{"hashedName":"6FvaJB","checksum":"vzG3","artworks":[{"id":"f92d2267-2cb6-459f-b8f4-07c280426a32","index":"2","hash":"BN5hJ"}]},"Moon Priestess":{"hashedName":"2uQZyK","checksum":"7zvx","artworks":[{"id":"fe304cba-fe68-4bea-a089-694d2e71a394","index":"2","hash":"Xj1vk"}]},"Moonspear Paladin":{"hashedName":"VyNoGN","checksum":"8Il1","artworks":[{"id":"4b963210-17ec-4cc9-9a83-f38a7692af0e","index":"3","hash":"7kpHb"}]},"Glowing Gearhulk":{"hashedName":"nE3xKP","checksum":"gApO","artworks":[{"id":"4efd2e1b-a113-49a0-8b09-a71768bc7f0a","index":"1","hash":"zpaoG"}]},"Goat Oracle":{"hashedName":"W0oJ8t","checksum":"l4pO","artworks":[{"id":"96dd861b-6cf4-403c-b701-35339b8bf72c","index":"0","hash":"1J1O3"}]},"Tranquil Herd Sagehorn":{"hashedName":"GYAAX6","checksum":"3mgT","artworks":[{"id":"eb74e363-ce23-4333-bf1a-9e45b5410528","index":"3","hash":"u80cq"},{"id":"ae7c802d-5bb3-4e5c-935f-0989f835981b","index":"3","hash":"CZ7CQ"},{"id":"d2520d33-6384-48e1-a0ac-2b40bcba9c67","index":"2","hash":"DBaQ/"}]},"Sunblessed Crocodile":{"hashedName":"VuZfwy","checksum":"/2Va","artworks":[{"id":"85566897-5ef8-42df-8c72-36628a9dd9fc","index":"1","hash":"Flqor"}]},"Kois of Duality":{"hashedName":"lxqKi6","checksum":"lJI/","artworks":[{"id":"e799950f-85b6-4223-b8ea-bc9ef93d3c23","index":"1","hash":"v9VZS"},{"id":"957a1f61-1c1b-4a33-82ab-c17bcc78d8f9","index":"1","hash":"2bg7t"},{"id":"957a1f61-1c1b-4a33-82ab-c17bcc78d8f9","index":"0","hash":"PMFkn"},{"id":"a05bda9e-586e-49de-8c32-0f6e47fd8831","index":"2","hash":"gsWLd"},{"id":"011a319f-3ec2-43a4-ae07-e31e88bbcfcf","index":"2","hash":"C1AJO"},{"id":"34302934-0ce2-4d12-9b6b-bcbfb2dd2748","index":"0","hash":"BQeBp"},{"id":"7515835a-18c0-492f-95bd-2b1b2539a4df","index":"1","hash":"KLhz6"}]},"Ivoryscar Eclipsion":{"hashedName":"BHwMmB","checksum":"7bGJ","artworks":[{"id":"219392dd-7217-4d08-88a4-07fe545e4e60","index":"0","hash":"VocbB"},{"id":"faebf78e-524b-4699-86cf-5a06ec2912c9","index":"0","hash":"Ljmja"},{"id":"ff5ef09d-ca5a-4078-8295-e865d3f5ef86","index":"1","hash":"XCB77"},{"id":"903c649b-d0e0-4b79-8d43-b2091e120243","index":"3","hash":"rCGmk"},{"id":"903c649b-d0e0-4b79-8d43-b2091e120243","index":"0","hash":"vcaUI"},{"id":"68687551-a06f-4550-bc88-6c49a58ac029","index":"2","hash":"VS2lz"},{"id":"ff5ef09d-ca5a-4078-8295-e865d3f5ef86","index":"3","hash":"5ZUDU"},{"id":"804192d1-d6b1-471f-8286-b2c1ae535674","index":"3","hash":"Jszyc"},{"id":"c2526578-9eb7-4bfc-b6cd-0f981333543c","index":"1","hash":"I+Os+"},{"id":"12474128-0863-4da2-aff8-997b73fe9878","index":"3","hash":"GNL7u"}]},"Fallen Angel":{"hashedName":"TuTJMF","checksum":"cwJd","artworks":[{"id":"65856a62-0cc5-4789-aeaa-4499b714d3e5","index":"0","hash":"AJjLI"},{"id":"9062fc96-38af-4b94-bb8b-58724ee3e784","index":"3","hash":"O7tpw"},{"id":"f0b193a4-3e5e-45a0-b6e9-a1b7fcfb4f49","index":"2","hash":"z56Up"},{"id":"2593ed6f-b67a-4e7f-a8f9-a36157ed8f86","index":"1","hash":"WT1sa"},{"id":"bce13b19-a5b7-4895-991c-a343e7295bea","index":"2","hash":"Od/+o"},{"id":"0852a4f6-c4cd-4d01-a719-8673b0ba2f74","index":"1","hash":"kF6r9"},{"id":"d19499fa-993e-4909-94ee-2b9c8761e795","index":"1","hash":"bLJ9G"},{"id":"93adb4ae-5796-400d-8a5b-0445ab93be6c","index":"3","hash":"Uw9Nf"},{"id":"cd0a04f4-a1cb-40f4-910e-eb46d3902255","index":"0","hash":"pB/AZ"},{"id":"02764ac5-6b69-4645-b186-6ada5c5faed8","index":"3","hash":"D66xa"}]},"Cavern Lindwurm":{"hashedName":"6YSUON","checksum":"ihkR","artworks":[{"id":"4cc82fb7-ff66-4625-86b9-bd6b6019e512","index":"2","hash":"qBHI8"},{"id":"172ae98b-46c0-4825-b85b-219a47dfecc0","index":"2","hash":"SUe1J"},{"id":"ab137782-70f1-4ba3-840a-49cf4fda7bbe","index":"3","hash":"auZvL"},{"id":"2780038d-6258-4c7a-a5e0-700cdfe423f9","index":"0","hash":"fN1pl"},{"id":"20fb2d42-8fe0-4690-82e2-b7936769540e","index":"1","hash":"+gd0T"},{"id":"bb160c1d-6202-4543-88a9-152dadcce248","index":"2","hash":"UIQm5"},{"id":"42ab612c-d4a4-4640-b0eb-a0098355068a","index":"2","hash":"rRBDk"},{"id":"42ab612c-d4a4-4640-b0eb-a0098355068a","index":"1","hash":"eVkTK"},{"id":"da9010de-44c1-42bf-8bbc-f7eb026c1882","index":"2","hash":"62XjA"},{"id":"bdfca501-4b58-4f97-83e7-bcf89c7e7f5e","index":"0","hash":"FCvu/"}]},"Cheerful Pixies":{"hashedName":"OiFUWm","checksum":"0Vqn","artworks":[{"id":"5af4932e-1176-4e5d-a15a-6e1142f73928","index":"2","hash":"OekBB"},{"id":"e6e0a2be-8317-493d-9a2a-cb227f34a270","index":"0","hash":"1L82H"},{"id":"a530c54d-e253-4627-adf2-00999c92b877","index":"1","hash":"UYW5O"},{"id":"05e7dc87-7c7f-400d-b1d6-3bce616d0bfb","index":"0","hash":"nKld2"},{"id":"a0c2bdad-9975-4339-8646-d109edd1ea08","index":"0","hash":"FQfOF"},{"id":"e7a204c6-76d5-4cd7-9a02-e06393503315","index":"2","hash":"o0Yfc"},{"id":"36d433e2-f591-4ea5-b62a-5cb266b18ca8","index":"3","hash":"oT3gU"},{"id":"e7a204c6-76d5-4cd7-9a02-e06393503315","index":"0","hash":"XOaF8"},{"id":"05e7dc87-7c7f-400d-b1d6-3bce616d0bfb","index":"2","hash":"IFPk0"},{"id":"b96d47c1-e03b-4dad-bc97-123945866ebe","index":"3","hash":"fvZdy"}]},"Cinderguard Scribe":{"hashedName":"URuLJr","checksum":"ABef","artworks":[{"id":"3583fb04-e10f-4436-a53d-ac6033c51e68","index":"3","hash":"iyyip"},{"id":"9bfd0617-c169-4772-bad8-21583764dcf1","index":"1","hash":"RkmaO"},{"id":"bd88a85c-62e5-4ed4-9515-3411b61e2af9","index":"2","hash":"WUsvZ"},{"id":"3506fd93-a468-430b-b68e-56e0adb3bfa1","index":"3","hash":"w9fjP"},{"id":"c5421a0e-601f-4a74-bd6d-431efe095978","index":"2","hash":"fTacu"},{"id":"522c30ba-cd4c-47ac-8df5-bc6a0c728eef","index":"0","hash":"9wJH/"},{"id":"f9350fe6-d4bf-4a09-be2d-6d486b1be787","index":"3","hash":"2pYB0"},{"id":"6364f253-c9ef-441f-a5a5-5cd35f3f48b4","index":"2","hash":"19qhU"},{"id":"6364f253-c9ef-441f-a5a5-5cd35f3f48b4","index":"1","hash":"T1JYp"},{"id":"7438c9cc-d782-4fee-9713-d3f301d7df3e","index":"1","hash":"sRHh1"}]},"Daredevil Duo":{"hashedName":"Z8eSHk","checksum":"6T2Q","artworks":[{"id":"7e117333-a3b5-48ce-84fb-ea1d5889f52c","index":"3","hash":"kSt5A"},{"id":"97f8b1ac-677e-491b-803f-a08321d0a5b3","index":"0","hash":"2ng/h"},{"id":"9b9f1932-7b85-4dc2-b89b-c5db313881fe","index":"1","hash":"VTgno"},{"id":"97d76fab-e567-498a-9cd5-fce2669c45a7","index":"1","hash":"QJUmd"},{"id":"e476fa49-0867-4ba0-b9df-543b391f48db","index":"0","hash":"tdIXB"},{"id":"c55ff963-8780-49f5-820d-fdb412bd03ab","index":"3","hash":"qkzRm"},{"id":"ecf46218-d382-4bbc-897b-729a460f33de","index":"0","hash":"S2JHJ"},{"id":"02663ec4-f725-4dc6-b3bf-a41c24089531","index":"2","hash":"wtzIv"},{"id":"960b0142-dad3-4a5e-9497-c50337bfa517","index":"0","hash":"Yx+s9"},{"id":"41adfac4-fb2e-4621-a9ff-3a8e7c83e591","index":"3","hash":"uy7Xa"}]},"Dewdrop Sprite":{"hashedName":"l48/cw","checksum":"cVxA","artworks":[{"id":"f82cb067-a26e-43e4-a7b7-872ad83abf92","index":"1","hash":"ApkSl"},{"id":"8fbe44e4-705c-4ee4-adbc-6e435546facc","index":"3","hash":"gmkUx"},{"id":"bce87206-d1bc-4ae5-b2a8-99df10be783b","index":"3","hash":"UrtCU"},{"id":"bce87206-d1bc-4ae5-b2a8-99df10be783b","index":"2","hash":"P0Es3"},{"id":"a9cd8a18-681f-4ef7-927f-65a2d9169d26","index":"0","hash":"cbE0K"},{"id":"9f273a40-8ff4-4686-8521-a3d630b0eaf9","index":"1","hash":"+Iu5V"},{"id":"7c0c6fe5-3d11-46e9-9fb2-27a3e4ad98d5","index":"3","hash":"zxo9Q"},{"id":"7c0c6fe5-3d11-46e9-9fb2-27a3e4ad98d5","index":"0","hash":"slump"},{"id":"e3dc4ec9-31d3-451f-b89d-f3942b80c042","index":"2","hash":"gz/Eq"},{"id":"7a2e29fb-bd98-4d30-88b2-8bfee70c4a47","index":"0","hash":"dFpva"}]},"Dragon Egg":{"hashedName":"a/JVEh","checksum":"YLI0","artworks":[{"id":"a4c0044f-a986-4aa9-87bf-000b67966a4b","index":"0","hash":"YreHq"},{"id":"1368b59f-6a3a-4f37-b704-dc0023c5a39b","index":"0","hash":"ya0bP"},{"id":"1368b59f-6a3a-4f37-b704-dc0023c5a39b","index":"3","hash":"OdkZe"},{"id":"3e4015d3-c57e-4d12-9ddb-df5fcfb9d19d","index":"0","hash":"Hs4Pm"}]},"Dustdance Efreet":{"hashedName":"ejJw3p","checksum":"SXK9","artworks":[{"id":"ccfe11ca-d68d-42dd-b1cd-d5aa6d3c9b8b","index":"2","hash":"7991c"},{"id":"ccfe11ca-d68d-42dd-b1cd-d5aa6d3c9b8b","index":"0","hash":"ZoJWx"},{"id":"fdd4f64e-d836-4c8f-9358-77cc88394b13","index":"1","hash":"An30J"},{"id":"f309aeec-173a-46f1-b16b-f5f15141815a","index":"0","hash":"3Q8Mi"},{"id":"f309aeec-173a-46f1-b16b-f5f15141815a","index":"2","hash":"jI5YO"},{"id":"f14bf8bf-3033-40a6-9792-dd0d2005d4a4","index":"2","hash":"wML08"},{"id":"f14bf8bf-3033-40a6-9792-dd0d2005d4a4","index":"0","hash":"UYfNL"},{"id":"f14bf8bf-3033-40a6-9792-dd0d2005d4a4","index":"1","hash":"K4ec9"},{"id":"1113a14a-e98b-4368-b526-2939a08de537","index":"2","hash":"o7mlL"},{"id":"2c70cf34-6786-4493-bc7e-731c0f15efba","index":"1","hash":"zGyaw"}]},"Roughlands Scourge":{"hashedName":"krpEuc","checksum":"xSnH","artworks":[{"id":"30dad8d4-0f43-43a0-b5ad-94bc8b2c85d6","index":"2","hash":"Kas63"},{"id":"6cad6adc-2697-4145-bdf0-efa0bf788436","index":"2","hash":"ITZzJ"},{"id":"6cad6adc-2697-4145-bdf0-efa0bf788436","index":"0","hash":"UQBuj"},{"id":"3583175b-766d-4e6f-b226-cb8e97cd3444","index":"2","hash":"vPwNt"},{"id":"9d3996dd-4cd9-4c61-9f0b-73b38822ab56","index":"1","hash":"hG81Z"},{"id":"26ae93ba-7660-44de-bc98-ff1f7b0710bb","index":"0","hash":"Wjh3m"},{"id":"add90753-1409-4816-a77b-7200b76c544f","index":"3","hash":"qh1vQ"},{"id":"dc135f3d-8b66-4450-857e-ed4b64a3e949","index":"1","hash":"sqLim"},{"id":"f552819f-bae0-4fdc-aec9-3c948fadca96","index":"0","hash":"wVsUM"},{"id":"93fb8cdb-1f21-49e7-be26-dc8ba099f499","index":"3","hash":"+jcXL"}]},"Shifting Sands":{"hashedName":"lEpOEn","checksum":"R6Lt","artworks":[{"id":"8b1af36f-4004-4f76-8321-39eadf6994de","index":"1","hash":"gs4Do"},{"id":"6b2dd4db-47bc-4351-b9cb-56165501015d","index":"0","hash":"Tr6vB"},{"id":"04b6c714-4150-4b67-bc7b-3b77d214c80e","index":"1","hash":"0vfE5"},{"id":"fef152fe-a54f-4993-8c0b-bdc6b255ff50","index":"1","hash":"oPDPx"},{"id":"a3b699ae-45ef-4e90-9cb6-6448c1dd6ef3","index":"3","hash":"H+L3H"},{"id":"a3b699ae-45ef-4e90-9cb6-6448c1dd6ef3","index":"2","hash":"3xSfD"},{"id":"f4b87c3a-3e3c-48fa-b94a-c0514613a2cd","index":"3","hash":"X9nDn"},{"id":"cea0e01e-1930-45b5-b5c8-3ad52ddb3142","index":"3","hash":"MImOf"},{"id":"ca73b5bd-6fc1-4339-9285-ae03c13a5f5d","index":"0","hash":"gqkkx"},{"id":"f43fb0f9-219d-46ea-84e7-cebd02ca67fd","index":"3","hash":"lk8eb"}]},"Torii Spirit":{"hashedName":"nAAz6h","checksum":"NEs3","artworks":[{"id":"855d9ad2-60fa-4317-90d5-dde695aa3863","index":"2","hash":"wKc6Z"},{"id":"ef31c8de-f61e-4972-86e9-aa9f1831afd5","index":"0","hash":"TAnr8"},{"id":"8785718a-3cef-4d6b-adf4-3f611a3b965e","index":"2","hash":"8ltGa"},{"id":"f0a7e593-e8a3-49a4-9357-69927b40e0a8","index":"1","hash":"h+w3e"},{"id":"f0a7e593-e8a3-49a4-9357-69927b40e0a8","index":"0","hash":"XjvEI"},{"id":"677914ad-f8cb-4855-b453-f47da8640844","index":"0","hash":"eWdhQ"},{"id":"0c2fcc58-1cd5-4e2c-9953-06ae99527acc","index":"3","hash":"BgWDF"},{"id":"cb83f03b-5441-4ab6-acd4-d6c23cfbf1b0","index":"3","hash":"GXLgl"},{"id":"cb83f03b-5441-4ab6-acd4-d6c23cfbf1b0","index":"1","hash":"VYMV7"},{"id":"11cea0b5-15f6-46ea-9c98-85147c5d0c1d","index":"2","hash":"6W2IU"}]},"Windkite Acolyte":{"hashedName":"bXd230","checksum":"P7Kv","artworks":[{"id":"ec1fb5cf-b226-482a-9fd2-005d6f927846","index":"1","hash":"JEdKt"},{"id":"c502c751-ced3-4cb3-aa77-ce7cf3c560d4","index":"0","hash":"Q59PV"},{"id":"15eb18a9-adcc-4ad5-bb1a-b9ca187fa7e5","index":"1","hash":"wTNsV"},{"id":"91bb5265-1010-4c14-8a17-c124ec7328be","index":"3","hash":"kbuxt"},{"id":"3459e7cd-50f2-4130-be4c-42546280c0e7","index":"3","hash":"Sn/8y"},{"id":"f6913507-2389-4765-a6a4-189bde5ce495","index":"1","hash":"uNrfl"},{"id":"f6913507-2389-4765-a6a4-189bde5ce495","index":"2","hash":"UuvOq"},{"id":"1be84c96-df08-4398-88f9-09e5ad8ff402","index":"2","hash":"2dbPb"},{"id":"59d1a1e1-529a-4cc6-b261-fdc197b29a2b","index":"1","hash":"Z7NpT"},{"id":"33065fbd-b99a-477c-aeda-1e82ea951a22","index":"3","hash":"zbylE"}]},"Blood Moon Scarab":{"hashedName":"kViNkZ","checksum":"XIov","artworks":[{"id":"f076bedf-28b1-43a4-bdf8-5e57ad378122","index":"3","hash":"2K3/R"},{"id":"2245d2f9-6faa-4d4c-9ddb-94e018ca54af","index":"0","hash":"wTw1D"},{"id":"2245d2f9-6faa-4d4c-9ddb-94e018ca54af","index":"2","hash":"O7g++"},{"id":"8c7e4ea8-e35f-4309-86b6-e6a9f1efaecb","index":"1","hash":"c+5RE"},{"id":"8c7e4ea8-e35f-4309-86b6-e6a9f1efaecb","index":"2","hash":"EY3gi"},{"id":"ae00d456-a481-4034-a8c2-fdb97fffe7f6","index":"1","hash":"80ViA"},{"id":"ae00d456-a481-4034-a8c2-fdb97fffe7f6","index":"2","hash":"86QpI"},{"id":"78ae5a97-8656-4c23-992f-61f8947a1950","index":"3","hash":"aNwpU"},{"id":"78ae5a97-8656-4c23-992f-61f8947a1950","index":"2","hash":"QzoMm"},{"id":"237ccf0b-0f9d-4e23-b6d4-df327207e61c","index":"1","hash":"Grssh"}]},"Amberlock Dragonling":{"hashedName":"N8ncwz","checksum":"22/2","artworks":[{"id":"31869c2e-79e0-44a2-bcb2-ef2489f226ad","index":"3","hash":"6vW3P"},{"id":"86e09484-75c2-4d9e-b33e-31faa3d4e251","index":"2","hash":"M9GEj"},{"id":"68e2c61d-f9ac-435e-8eb9-44ef82724758","index":"1","hash":"7NRoH"},{"id":"02a937b0-dc30-4b61-a80a-775950a47d1e","index":"0","hash":"YxvuT"},{"id":"f8926069-73ab-4045-b918-9cb77758a03b","index":"3","hash":"QQSYx"},{"id":"a02f660a-1dce-436f-acb5-465e63f5bbc5","index":"1","hash":"2WVrf"},{"id":"0e687280-8a8e-4bab-ba7e-71eecfd6f625","index":"2","hash":"HF4h+"},{"id":"5e110d2e-a7e4-436b-bb11-4fb86e1580e9","index":"3","hash":"mE1Is"},{"id":"5e110d2e-a7e4-436b-bb11-4fb86e1580e9","index":"2","hash":"w4NLb"},{"id":"750ed738-29ba-42b6-8f6f-d878ddac70d4","index":"1","hash":"kI00m"}]},"Dragonfire Warlock":{"hashedName":"VoBAnn","checksum":"QBZn","artworks":[{"id":"e1671c8d-c48c-402d-addf-9a0fccad1761","index":"0","hash":"lO8/u"},{"id":"ba533218-851c-4bf4-a8d6-1d40dd59d983","index":"0","hash":"2+7e6"},{"id":"01e8e033-593c-490d-a32f-a166ab8baa48","index":"2","hash":"QF4Z5"},{"id":"5eca18e5-b521-4e2a-9848-bc98673ae4d2","index":"0","hash":"kf5SZ"},{"id":"914ae491-f842-47a7-972e-d9a4a84c90f6","index":"0","hash":"dpGQc"},{"id":"50351124-cb8d-40c5-ba32-ab7ed7975d03","index":"3","hash":"XRb2I"},{"id":"9b90030e-860f-496a-a734-a45969d1b0dd","index":"1","hash":"tpk8F"},{"id":"54eedfaf-453e-4a49-bd5b-d4012761a293","index":"1","hash":"+6K9H"},{"id":"6e8217f3-8ac2-45b0-8dc4-ef5352b479ea","index":"2","hash":"8guAQ"},{"id":"12dd80f9-bb06-4d38-91d8-e146559471c0","index":"0","hash":"NFolE"}]},"Dragonwind Harbinger":{"hashedName":"d8zgrk","checksum":"/L/E","artworks":[{"id":"e4901e8f-dc64-4a32-8b4e-4db18f9edb34","index":"2","hash":"Xynfo"},{"id":"792d59ef-82cf-4773-9eb4-65105c9208ec","index":"2","hash":"NgwLv"},{"id":"61d71d29-7f19-4719-9f9d-b595a90e7eac","index":"3","hash":"99XWs"},{"id":"8f47bfa6-8da8-478d-aba1-dff1a5520f1c","index":"0","hash":"sW3aU"},{"id":"841174db-5c68-41e8-819a-09fa028c5943","index":"3","hash":"8F+Bp"},{"id":"841174db-5c68-41e8-819a-09fa028c5943","index":"0","hash":"K7iSQ"},{"id":"53760255-c6fe-4c4c-ac76-95aa017993f9","index":"1","hash":"Z9uDk"},{"id":"87f09264-db69-471c-a5b1-db98d924778f","index":"0","hash":"XcF2r"},{"id":"87f09264-db69-471c-a5b1-db98d924778f","index":"3","hash":"09Aec"},{"id":"b5789562-2e2e-4ceb-8443-0ae424a3c7dd","index":"3","hash":"hv6MU"}]},"Gashopper":{"hashedName":"xVCXKi","checksum":"2zI/","artworks":[{"id":"aa3828cc-da5b-44fd-a991-7dfa8d358eca","index":"1","hash":"H0Opv"},{"id":"bb66d639-f343-4845-af2a-5eb193006647","index":"0","hash":"+Vmcx"},{"id":"9d22a6ef-3cfd-4390-83a1-bcb607bfc60e","index":"0","hash":"XJcTP"},{"id":"9d22a6ef-3cfd-4390-83a1-bcb607bfc60e","index":"2","hash":"+Eadr"},{"id":"4a4fcd20-cf99-4f08-98be-e4a9a21447fd","index":"2","hash":"qR2RI"},{"id":"edce3cff-dccc-4dd6-927a-c86b99379750","index":"1","hash":"RJ0Qr"},{"id":"712bc1b1-a311-4c9e-8fd3-9084faf62db5","index":"1","hash":"Z48Gb"},{"id":"712bc1b1-a311-4c9e-8fd3-9084faf62db5","index":"2","hash":"Km9Kp"},{"id":"0ac155c4-dccd-49ea-a6ba-b70dd8d8e9a3","index":"2","hash":"S2LxX"},{"id":"4675fbf5-6bfc-4c8a-9092-aaf4e3643f28","index":"2","hash":"LTF3k"}]},"Glinteye Hoarder":{"hashedName":"e8/Qo1","checksum":"DFx5","artworks":[{"id":"8ccfe4e3-0dd5-4f9c-be98-1629ec29694f","index":"0","hash":"RQPwW"},{"id":"8ccfe4e3-0dd5-4f9c-be98-1629ec29694f","index":"2","hash":"4Tm8P"},{"id":"47e93cbb-0e71-491a-a49b-5685172b96b1","index":"2","hash":"8p3E6"},{"id":"c0bbf41e-da40-447a-8817-ba761c755907","index":"1","hash":"SPrx8"},{"id":"e27864a6-cc07-4984-b181-922b584c0d96","index":"3","hash":"wMiuC"},{"id":"0a1168a7-16a3-4022-b822-fd13a508a624","index":"0","hash":"/hAhT"},{"id":"e30e77bd-955e-4e8e-afe4-eae7161982c4","index":"3","hash":"StvJf"},{"id":"eaad0536-abea-4999-883c-e3e793929cf4","index":"3","hash":"/svjM"},{"id":"a3874385-0194-4c0f-ba14-08b4d7628a67","index":"1","hash":"5dfZg"},{"id":"8c585bc8-5180-439e-8adb-c3a47c0150fe","index":"2","hash":"XL/C5"}]},"Raijin's Familiar":{"hashedName":"J52IIY","checksum":"6J6p","artworks":[{"id":"99049fea-fc5d-4752-b9db-6d8c91ccc8ae","index":"2","hash":"phVBL"},{"id":"a57b5b64-f263-4fdf-af6b-1b93580bfe5e","index":"0","hash":"xhofP"},{"id":"7fc25a68-b33f-47f1-a6ec-9553717b1c97","index":"0","hash":"uJwLb"},{"id":"7fc25a68-b33f-47f1-a6ec-9553717b1c97","index":"1","hash":"tU1GP"},{"id":"9f59a1ed-24af-4d99-acaa-6a2a05df2427","index":"3","hash":"LMi4S"},{"id":"8572f917-df31-4408-8707-1d30d6ca5130","index":"2","hash":"1Qwnn"},{"id":"fb929c6c-57e6-433a-a266-d6503efa9f59","index":"3","hash":"75yLR"},{"id":"2ddb8064-c0f9-4c6e-bd7c-5450e649e0ba","index":"1","hash":"CN8gA"},{"id":"2ddb8064-c0f9-4c6e-bd7c-5450e649e0ba","index":"0","hash":"WzxVw"},{"id":"c9877abe-5367-4550-95bd-009c5ca1c395","index":"2","hash":"9cZ4a"}]},"Runecursed Wyvern":{"hashedName":"VaOnjU","checksum":"+jBo","artworks":[{"id":"304afcfd-7894-408f-9075-b9665b0da9bb","index":"1","hash":"tCbQv"},{"id":"3f700745-93e9-491e-b302-0f3b8129cd3a","index":"3","hash":"bnGkY"},{"id":"efc96ed0-d87b-4d29-bb86-f29795728bf8","index":"2","hash":"wyh0n"},{"id":"b6935539-efed-401f-850a-d485cb53a209","index":"2","hash":"zajn1"},{"id":"b1f8f3d5-445f-4c75-8c69-dc3c00dd6a2a","index":"3","hash":"oLC54"},{"id":"b1f8f3d5-445f-4c75-8c69-dc3c00dd6a2a","index":"1","hash":"MFaKk"}]},"Skulloath Lootclaimer":{"hashedName":"N9RWbv","checksum":"aaNA","artworks":[{"id":"b782234a-ae27-4ab3-a874-11519512ecce","index":"1","hash":"0yFqe"},{"id":"bace0219-18ab-4fad-b1cf-6dd7f636ba09","index":"3","hash":"zR6KD"},{"id":"bace0219-18ab-4fad-b1cf-6dd7f636ba09","index":"1","hash":"cdkDk"},{"id":"48fb748c-ced1-4a11-b902-08569b23ea3e","index":"3","hash":"Ql7xl"},{"id":"648f33e0-f155-4776-b3ef-cb6a2da47ad2","index":"0","hash":"idSkK"},{"id":"88722dbd-81e5-4a88-b7b1-4d119407e4eb","index":"2","hash":"A619V"},{"id":"ac379b8f-0976-49e8-9984-afd4fa85d72d","index":"2","hash":"6p/0w"},{"id":"ac379b8f-0976-49e8-9984-afd4fa85d72d","index":"0","hash":"XIzyS"},{"id":"ce81bdef-692d-43ea-9dce-a4b313702bd0","index":"2","hash":"J2ZTh"},{"id":"92e4fd9a-ec61-456e-ae1a-ccf89544238d","index":"1","hash":"c0lU3"}]},"Spell Cat":{"hashedName":"1uaB+E","checksum":"J/9o","artworks":[{"id":"23c28003-cb9d-4252-b47e-eb31b79c4746","index":"3","hash":"evip4"},{"id":"c014fa78-9b56-4e92-9380-05f3c1bc63f2","index":"3","hash":"r4OZ8"},{"id":"c014fa78-9b56-4e92-9380-05f3c1bc63f2","index":"0","hash":"f+pYG"},{"id":"ea69db27-0094-46a2-957d-df9c6587cd8f","index":"1","hash":"Mnwg8"},{"id":"d8a56be5-0fe5-434b-a77a-b6146873ea1a","index":"3","hash":"Pz9zX"},{"id":"d8a56be5-0fe5-434b-a77a-b6146873ea1a","index":"0","hash":"3BDnk"}]},"Vermillion Firebird":{"hashedName":"vcL66O","checksum":"OxDS","artworks":[{"id":"855584b6-ff81-449c-bfc8-776b89e2e1b6","index":"2","hash":"R5lKu"},{"id":"855584b6-ff81-449c-bfc8-776b89e2e1b6","index":"3","hash":"MjpqK"},{"id":"8267de13-464b-4475-8b89-635cac0d70bd","index":"0","hash":"ePf0J"},{"id":"855584b6-ff81-449c-bfc8-776b89e2e1b6","index":"0","hash":"ZIlHS"},{"id":"ce13cd47-a205-4d28-96b0-bdf906fae89f","index":"0","hash":"i78W6"},{"id":"a18746cf-975e-483a-9c0c-94c134cf6af2","index":"3","hash":"2P928"},{"id":"a18746cf-975e-483a-9c0c-94c134cf6af2","index":"1","hash":"5v0N7"}]},"Oasisdweller":{"hashedName":"GqI5ar","checksum":"jg3Q","artworks":[{"id":"64365801-a467-48b5-80fe-b2e14b46c622","index":"3","hash":"JnGv+"},{"id":"edfa0ecc-62fe-4e23-8bad-51f3f37c3e52","index":"0","hash":"QcXDe"},{"id":"90b1ef17-1840-43a4-a96b-9d42245755e5","index":"2","hash":"p85/A"},{"id":"4529965a-161b-46fc-84ef-11b6aa6505c0","index":"1","hash":"k2dt3"},{"id":"0c3b1178-de16-46bc-a164-f1739f41cd16","index":"0","hash":"DbWNl"},{"id":"ebc002b1-7bb9-479e-a1ce-ea1c8ddf987b","index":"1","hash":"s7a6r"},{"id":"fcedc117-8f07-44fd-9b27-38403dc905eb","index":"2","hash":"VMCNf"},{"id":"fcedc117-8f07-44fd-9b27-38403dc905eb","index":"1","hash":"uHMoZ"},{"id":"61c81789-079d-4284-bc11-8f18bf858e7a","index":"0","hash":"GG80A"},{"id":"54179720-6bdf-4c71-8029-954ac967324e","index":"2","hash":"C31jE"}]},"Cinderguard Irregulars":{"hashedName":"U1xDHF","checksum":"rF8s","artworks":[{"id":"9abdcae0-7389-454b-bde3-fb534aec9fa4","index":"1","hash":"0S+7J"},{"id":"21aae87c-bcf0-4967-94c8-66c12bd2dd5f","index":"2","hash":"qwYXS"},{"id":"ff085a28-2be3-400f-b0aa-dfbaad7ad260","index":"3","hash":"GRwnE"},{"id":"7daae98b-96af-490a-abb0-c40d53d449c6","index":"1","hash":"VUNGq"},{"id":"7dd032d6-0ed5-4d3f-926c-322526d5acea","index":"3","hash":"nmyfN"},{"id":"78be4041-6983-4fec-ac2f-158748bc0f07","index":"1","hash":"/aMZv"},{"id":"081fdde2-8231-41d5-aa5c-be3ff2f37b5d","index":"2","hash":"2dCT/"},{"id":"e641b986-4bf2-46ee-bff1-f15abfe257b6","index":"0","hash":"H+KGr"},{"id":"7f7e7244-f70d-4340-bc00-db8ba5869d51","index":"0","hash":"3raN7"},{"id":"fe6e9b6c-1cca-4a3d-b1ff-7bb7fd6ebc36","index":"0","hash":"TsCoQ"}]},"Galeweaver":{"hashedName":"ppU0P/","checksum":"pvlY","artworks":[{"id":"ded5b3c8-a989-40e4-8be3-5ac67cf41736","index":"0","hash":"6bDLQ"},{"id":"7f5227db-8efa-4198-aad8-a7303c4834f9","index":"0","hash":"GIfol"},{"id":"affa39b4-9e17-48c4-8895-78b1f433b9f7","index":"0","hash":"9nNCz"},{"id":"5b8a0ee5-409e-4609-8aba-0c49858830f9","index":"3","hash":"eHBkF"},{"id":"5b8a0ee5-409e-4609-8aba-0c49858830f9","index":"0","hash":"yauyB"},{"id":"436c6169-6856-4831-9b5e-36c538fafa7c","index":"3","hash":"vAhU0"},{"id":"658a4dd0-bf6d-47e7-86d8-52ee52a8f214","index":"2","hash":"1/lkg"},{"id":"7bb8e808-62d2-41bb-8749-200a9089a3e9","index":"2","hash":"Y6/8n"},{"id":"4ccb8031-ae89-47b6-a633-e16eac63166b","index":"3","hash":"G3BVh"},{"id":"7f81eb9e-f062-46de-9105-f93730a4e7fb","index":"0","hash":"JqlY3"}]},"Infernoblight":{"hashedName":"mmmpa2","checksum":"rubt","artworks":[{"id":"33f7cc2c-e93d-4e2c-9b65-000f7fec5b4d","index":"3","hash":"2FByq"},{"id":"d85c9fc4-fcbf-4427-9461-c7d69924fd22","index":"3","hash":"SylV1"},{"id":"ded1343a-822d-4000-b96d-307220437a47","index":"3","hash":"cWi3k"},{"id":"7b986382-842d-4894-bfa5-8f3a13c28048","index":"2","hash":"LjjWA"},{"id":"7b986382-842d-4894-bfa5-8f3a13c28048","index":"1","hash":"h8F+h"},{"id":"3ece9766-fbca-4a9f-b43c-ceacdfd34356","index":"0","hash":"vC0tr"},{"id":"23146584-f12d-4df7-9044-bc3fddd5aed1","index":"2","hash":"an5gE"},{"id":"e7c5e4fe-638b-4178-857e-6623f117ac1e","index":"3","hash":"62guT"},{"id":"d1d4e43a-6294-4cca-b9e9-a8a9b7c14773","index":"2","hash":"YG0C6"},{"id":"1b37b6ab-c626-42c3-a564-3b3f1a292370","index":"3","hash":"qKk46"}]},"Raijin":{"hashedName":"5n5lgU","checksum":"nNOU","artworks":[{"id":"1c379fb0-c7fe-4bce-a2e2-c1046dca0a59","index":"3","hash":"hMPBs"},{"id":"1c379fb0-c7fe-4bce-a2e2-c1046dca0a59","index":"1","hash":"KQDWn"},{"id":"1c379fb0-c7fe-4bce-a2e2-c1046dca0a59","index":"0","hash":"pGTfD"},{"id":"032d003e-cfc5-416a-b659-1bdded298c0e","index":"1","hash":"K0wZX"},{"id":"de56f839-6491-46cf-880d-6d928a2517da","index":"0","hash":"JR/1N"},{"id":"83e9cfe5-7b3e-4733-9009-d3e420db215a","index":"1","hash":"eEZHK"},{"id":"5764c6a2-ac2a-45d1-bd44-3056e5b71fde","index":"3","hash":"MsZXk"},{"id":"dabe2c88-7609-4d23-9be4-b6d03f5043ec","index":"2","hash":"fJP20"},{"id":"22f743bd-9c45-49eb-bcae-584391aba2aa","index":"1","hash":"fVHRs"},{"id":"16ee0dc4-08e6-49e0-be6c-5041c7b5d4f9","index":"1","hash":"3FwJw"}]},"Volcano Embodiment":{"hashedName":"Zgl5/P","checksum":"mzFy","artworks":[{"id":"b3f1d5b4-d271-4bb7-9615-dec247ec2937","index":"0","hash":"Z4iIs"},{"id":"13f74e45-15bf-4673-a15e-3672c00526da","index":"2","hash":"MNWZs"},{"id":"710d0cf8-ce38-4aa4-b3f2-876f350c95e5","index":"1","hash":"QpnsW"},{"id":"670cd204-5704-4f12-9125-5eb354177f5f","index":"2","hash":"DC5/E"},{"id":"7ab22aed-daaa-486c-bcb0-51549f984fe3","index":"0","hash":"7Pd5J"},{"id":"22bb3e8d-5c52-4c44-8587-02c99977f143","index":"0","hash":"iOi2J"},{"id":"eca24b96-706c-4dc3-98e0-b7e7167890f1","index":"1","hash":"fP5yu"},{"id":"c01595f3-8df5-40fb-ad79-c4ab3f4993bf","index":"3","hash":"2Meie"},{"id":"c57f1fec-7402-4dfa-a0da-3df1bc5a18a7","index":"2","hash":"pl9Up"},{"id":"89af2c6d-773c-4b37-a02a-c29797ab5507","index":"2","hash":"D1xD5"}]},"Shardhorde Leviathan":{"hashedName":"XfHlLj","checksum":"2drh","artworks":[{"id":"f04b4fbf-83ad-4f50-9c3a-68843e69ef11","index":"2","hash":"LIUdB"},{"id":"23732ab2-74d0-4739-baaf-5e6c23e8873a","index":"0","hash":"2cdDs"},{"id":"cb44e85d-870b-4bc6-8948-450c772daf5c","index":"0","hash":"CQRvH"},{"id":"258f8be4-8fc8-47e9-9423-4d7e9f7e209b","index":"0","hash":"If4kN"},{"id":"97987280-b216-408a-9bcb-dd348cfcb803","index":"1","hash":"ErOm6"},{"id":"736a8fe4-c031-4266-a180-8d5fa8d7a20c","index":"3","hash":"JjnIK"},{"id":"f4364281-c341-4325-823b-cc159f62e3fa","index":"3","hash":"0xzV3"},{"id":"f4364281-c341-4325-823b-cc159f62e3fa","index":"1","hash":"H8eDg"},{"id":"3ffc8199-7676-44a0-b357-0e6a826b2531","index":"1","hash":"r+wen"},{"id":"c0768680-bd4c-4545-846f-002afd6a854b","index":"0","hash":"uZVSU"}]},"Tectonic Shifter":{"hashedName":"7c9/v2","checksum":"AvrZ","artworks":[{"id":"04e07353-17ab-4846-84bc-818bc402f09d","index":"1","hash":"qwkqR"},{"id":"e8e96f76-94bd-41ae-b1bd-4ca96aebdd1e","index":"3","hash":"WYu1i"},{"id":"ee08debf-6dfa-4c1a-b68d-af2815e27ecd","index":"0","hash":"JoWlL"},{"id":"a5b23374-c9e0-4cc3-ac9e-7cc693ab07b6","index":"1","hash":"SRbI9"},{"id":"da48772a-b4d4-44f8-8d55-428c4b7750df","index":"1","hash":"eOQoX"}]},"Dragon Rider":{"hashedName":"4byTYV","checksum":"Y4Cd","artworks":[{"id":"f29821d3-a78b-46a9-ab7b-9b476d6ecfd7","index":"1","hash":"3c55f"},{"id":"7f15e033-4d9d-48a2-9a39-7197c3b9bf07","index":"3","hash":"t0EB7"},{"id":"a6b8108d-1bb5-42d2-a7a0-28095eb3d2c2","index":"2","hash":"QDy6z"},{"id":"60403217-9653-4c7f-8bd1-52389abddd0b","index":"2","hash":"MUYUw"},{"id":"35a72dcd-bf6d-4211-a3ec-b4a56e9266de","index":"3","hash":"QZBLq"},{"id":"64811c7a-9306-4518-8d43-b94ca602125b","index":"2","hash":"nRc3S"},{"id":"4f36ce57-0d46-485b-824d-f5324b716d84","index":"1","hash":"IL8OP"},{"id":"b7fa891c-92aa-4309-9f37-1140cd8df7b3","index":"2","hash":"s3olr"},{"id":"64a2413c-9261-4124-ba7d-e64c2319aae0","index":"0","hash":"1SDZA"},{"id":"95d4bd24-c3f9-417f-be00-e2b02341a172","index":"0","hash":"ctTkn"}]},"Starfall Shaman":{"hashedName":"ikKNqy","checksum":"0vL8","artworks":[{"id":"0d462342-adfb-4bc1-8852-2f568fbc9684","index":"2","hash":"UFDu1"},{"id":"eb6b6ed8-09d8-4cb7-8e72-89daeeb5ad45","index":"1","hash":"z+oCD"},{"id":"0bfb1ddb-5317-44ca-ac28-18bec4484bb2","index":"2","hash":"FmFQ2"},{"id":"fc65d230-0b7a-4bbd-9653-6fa105e5bcec","index":"3","hash":"gLPoN"},{"id":"48703433-d069-4669-a233-4fb736b88afa","index":"2","hash":"f5sz2"},{"id":"48703433-d069-4669-a233-4fb736b88afa","index":"0","hash":"NnlVZ"},{"id":"3500932c-0e0c-496e-8393-7f54603731c9","index":"3","hash":"FP4xH"},{"id":"888400b6-fc24-4382-9b4f-cb536d1c6259","index":"2","hash":"auwyJ"}]},"Cinderguard Flamebearer":{"hashedName":"HaBGZm","checksum":"Ee/G","artworks":[{"id":"ad69563e-8c74-41b0-8e13-8b39afa3b3cf","index":"3","hash":"z8f7b"},{"id":"ce3cd5be-146d-4747-a725-96d02fce6988","index":"3","hash":"d097C"},{"id":"e1308eb5-a0fa-420c-983e-4f03c2e8e1b1","index":"3","hash":"roKjq"},{"id":"0c8ecc9c-0eba-4e1f-88ef-eb8a6b5bb902","index":"0","hash":"JhEX1"},{"id":"915e002d-0994-4e3b-9b5b-10849e3c35ad","index":"2","hash":"CCvrG"},{"id":"eea88919-f1b3-40c0-9f43-d0e3f3705e14","index":"2","hash":"Hkgqb"},{"id":"727e14da-bc4a-4671-9e13-4f06e7007152","index":"0","hash":"87Jsa"},{"id":"24410310-250b-4dfc-957c-f04fe0d1851b","index":"0","hash":"l6Dds"},{"id":"49af1a65-37b2-43e7-abfb-fec1ef5ae6d3","index":"2","hash":"M8yHZ"},{"id":"c49fa673-bcd1-49dc-a65d-b262aa8d349c","index":"3","hash":"X0nuZ"}]},"Tidecrasher":{"hashedName":"njlVFn","checksum":"3O2M","artworks":[{"id":"b85e9529-2c1c-43be-8887-f8653d2daa3e","index":"1","hash":"sVuC8"},{"id":"cbc1003a-54e1-4023-a949-d6248d86958a","index":"1","hash":"7DCKe"},{"id":"14907b72-ac7b-441a-89c1-206aa74ae3cc","index":"3","hash":"F7vrF"},{"id":"da05031f-b161-4dbf-82ed-34f56ec60f8b","index":"3","hash":"Y1Bgp"},{"id":"da05031f-b161-4dbf-82ed-34f56ec60f8b","index":"0","hash":"PUOHj"},{"id":"36f45aba-7dd3-4234-a291-4a6bd6317f10","index":"2","hash":"qshTP"},{"id":"36f45aba-7dd3-4234-a291-4a6bd6317f10","index":"0","hash":"bswVN"},{"id":"cb5ae9cc-bb0c-4b23-93f2-9aba3eead611","index":"0","hash":"phNi5"},{"id":"5346acfb-9c48-4258-a97e-45266d64b6d2","index":"3","hash":"W4jSu"},{"id":"89be5e2a-6702-40e7-bb2c-87dce748f051","index":"0","hash":"18H3g"}]},"Eons-old Dragon":{"hashedName":"7zJa6b","checksum":"Y0hE","artworks":[{"id":"ade40824-39ca-4001-a6f9-b17abaa7f8c9","index":"2","hash":"SzB6C"},{"id":"237069bf-4281-4ab7-875e-331a4121cc5c","index":"2","hash":"kC9y/"},{"id":"b817370e-a391-4a6b-9688-f381c88b69b0","index":"2","hash":"MQmcx"},{"id":"1147f4d1-0ebc-4af6-a726-d02c68d60b73","index":"0","hash":"0kFYV"},{"id":"1147f4d1-0ebc-4af6-a726-d02c68d60b73","index":"2","hash":"ChWFP"},{"id":"aad8229e-1d42-48dd-8179-36ff489b78e3","index":"2","hash":"31MNC"},{"id":"01a4f043-f235-41b9-8d46-7b35d6f18030","index":"2","hash":"gYgfW"},{"id":"c0cf7df8-c1a5-454a-bfd0-19b8243d58cc","index":"1","hash":"bFgz8"},{"id":"16ae4b70-d224-42db-b6b6-ecf2124ed295","index":"0","hash":"Sb2uk"},{"id":"4623ba22-8900-4ec0-baf7-811a3eacf3be","index":"1","hash":"kzajM"}]},"Shardhorde Crystalfang":{"hashedName":"nHryPG","checksum":"nM56","artworks":[{"id":"16b422f4-9fd2-4bb1-9674-585e0409a383","index":"3","hash":"8F19y"},{"id":"ce917096-e668-418b-8741-693ddbec1b5e","index":"3","hash":"S/uzB"},{"id":"dce6223e-4d4d-4a94-b8ed-94d249a1b876","index":"2","hash":"PRNZn"},{"id":"993d4901-e479-4c23-8e37-374cc886632f","index":"0","hash":"7CA5s"},{"id":"44b8a171-093e-48a9-b7dd-0eb68cf31160","index":"0","hash":"tJSTV"},{"id":"c6262938-a0bb-4c14-a59f-2cd741aebb5d","index":"2","hash":"qKRku"},{"id":"2d36ed03-9eb8-4873-a6b6-490fa41bd145","index":"2","hash":"QUngG"},{"id":"64fe4f62-cd24-4b28-8008-3a9184077878","index":"1","hash":"DkXlU"}]},"Pyroclastic Zombie":{"hashedName":"7D0vL7","checksum":"RmIB","artworks":[{"id":"66f83bd6-353d-4924-b469-c22fdaf65162","index":"2","hash":"v4zCB"},{"id":"21d93227-da2e-4a58-8af8-8d84f202d465","index":"1","hash":"gURiX"},{"id":"de56e6d6-8aad-4bd2-87f9-f0c5f1ec9d8d","index":"0","hash":"zweXi"},{"id":"57f88d60-31a2-4dbc-a2ac-7dd5f12faad2","index":"1","hash":"rXKZi"},{"id":"2148c090-768e-48c9-837a-fed7af76f1c3","index":"1","hash":"FQIjT"},{"id":"59597b80-8b3f-4d4b-806c-dcf5365bda0f","index":"2","hash":"+ydUx"}]},"Wasteland Overlord":{"hashedName":"4HbG9G","checksum":"deSt","artworks":[{"id":"721910bd-16ac-4a72-aa68-a72421d90c86","index":"1","hash":"NVIe0"},{"id":"e4ab81e9-3fd7-4319-9c94-67577b4742fc","index":"1","hash":"3sU/x"},{"id":"672168db-d4c7-464a-9a08-3f0b7300f117","index":"0","hash":"19NEa"}]},"Skulloath Marauder":{"hashedName":"elg27K","checksum":"zIKH","artworks":[{"id":"9837fc27-5358-46a5-b2d5-4b2eccd5199c","index":"0","hash":"GT1nw"},{"id":"1611e437-755b-410f-b205-ccef721ff7ae","index":"1","hash":"sx6p8"},{"id":"1611e437-755b-410f-b205-ccef721ff7ae","index":"2","hash":"KND40"},{"id":"d0513e19-1ac0-4d65-b7d1-c084eaa39eb1","index":"1","hash":"6huqO"},{"id":"cb5a0d7d-cfdf-4743-8f88-5b4c20641ec8","index":"0","hash":"1ncI3"},{"id":"0e38f1ce-471e-455b-890a-7a46d67a8c3c","index":"3","hash":"3XCqB"},{"id":"651c5e10-daa8-4734-8d9e-45e6e71afe5e","index":"3","hash":"jKoSO"},{"id":"b305aa77-1f10-402e-b176-99e909abfb9d","index":"3","hash":"R/8Ch"},{"id":"3f1e36e7-8385-4701-8ad1-a8a145d654d4","index":"2","hash":"92crB"},{"id":"05ead972-45fd-4d93-b3b6-736da52e9d68","index":"1","hash":"JY9hN"}]},"Alchemist's Incense":{"hashedName":"dyGFSn","checksum":"fEzv","artworks":[{"id":"acb30613-f9af-4a64-81e9-e6b568cba824","index":"2","hash":"NntWp"},{"id":"f8601415-70ff-4ce2-aed0-f550f9d08f3d","index":"0","hash":"VO0N8"},{"id":"f8601415-70ff-4ce2-aed0-f550f9d08f3d","index":"1","hash":"Cn0Zs"},{"id":"f8601415-70ff-4ce2-aed0-f550f9d08f3d","index":"2","hash":"ZqoX7"},{"id":"2a292725-24e5-4da2-ae58-2f0eadedb275","index":"2","hash":"hl6yQ"},{"id":"3b50b5d8-08a1-4b97-8366-8e40ccb84ae0","index":"3","hash":"5kx1g"}]},"Ambrosia Bee":{"hashedName":"e97hNs","checksum":"nNxk","artworks":[{"id":"86b3223b-25b2-49c4-9ba0-56eef1eedbbf","index":"1","hash":"XnCpm"},{"id":"aea064ae-88ea-47ba-a280-c9e470d12b69","index":"2","hash":"vwD7a"},{"id":"8e48c3ce-1b90-4253-abcc-2da0b25ad425","index":"1","hash":"ojkw/"},{"id":"64dbf7d3-51d9-49d7-826e-908e3f7f1760","index":"1","hash":"mK4tD"},{"id":"64dbf7d3-51d9-49d7-826e-908e3f7f1760","index":"0","hash":"1O3Te"},{"id":"3f24055e-e0a2-47c1-8470-64c33d0f6866","index":"2","hash":"x4LPU"},{"id":"7ebb9929-e2ad-442f-b9a8-ea6f82e7e006","index":"3","hash":"v97Bz"}]},"Filthy Peasant":{"hashedName":"Kb8r0F","checksum":"87Ya","artworks":[{"id":"8681b697-3ab5-4ab3-8d4d-13ada408b719","index":"2","hash":"2oBjD"},{"id":"ef758448-e6c6-4375-a43a-ca7ef038fb25","index":"0","hash":"JlDEV"},{"id":"4ebf7027-ca2f-44a2-9f30-1afa66999935","index":"3","hash":"J4kbr"},{"id":"49574fbd-fd5a-42b4-ba67-f1956f3a5a0d","index":"1","hash":"butH4"},{"id":"460856be-5a5a-4e01-880f-a9cc4ae12568","index":"3","hash":"uuLM6"},{"id":"b950d7fe-0373-44bc-876b-60878bbaa0ab","index":"1","hash":"0emhf"},{"id":"284a6f4c-c46f-4a01-9341-585d947f44bd","index":"1","hash":"MmWJ0"},{"id":"cb3ef15b-833e-4f93-9735-f5e82d3fc66a","index":"0","hash":"AC3a9"},{"id":"1c7bdaca-4cf8-4915-ae8e-aacfc7c209d2","index":"3","hash":"tTHBt"}]},"Ironstride Courser":{"hashedName":"8TQg78","checksum":"Bmwg","artworks":[{"id":"8d1657bf-8d7f-4836-b474-5c1cff1916c0","index":"2","hash":"eTQI1"},{"id":"fdf1b8f9-ccc0-4aaa-8191-4fab233512d4","index":"0","hash":"+t4Fq"},{"id":"54b00b16-65a7-4baa-b8e3-37fd71f85d8f","index":"3","hash":"SvKYf"},{"id":"a70a1341-a55b-41e0-af0e-c975f47bf9b4","index":"0","hash":"mDmLg"},{"id":"81588d14-ce8b-416b-ab7d-351ff14b045b","index":"1","hash":"a0w89"}]},"Pocket Dragon":{"hashedName":"BPu3NC","checksum":"+8Kf","artworks":[{"id":"4ff343f0-4546-4f8f-bb97-7214850f4953","index":"1","hash":"xV2c/"},{"id":"4ff343f0-4546-4f8f-bb97-7214850f4953","index":"3","hash":"YhFjC"},{"id":"f73f0149-0f46-4732-a763-e53b93a1af4c","index":"2","hash":"aBTVw"},{"id":"c05760f1-f3cd-41ec-8511-d7268f2ece64","index":"3","hash":"a+D0M"},{"id":"c05760f1-f3cd-41ec-8511-d7268f2ece64","index":"0","hash":"7PAAI"},{"id":"c05760f1-f3cd-41ec-8511-d7268f2ece64","index":"2","hash":"lGM4u"},{"id":"14c4af69-8e71-4174-ab81-7b2daa2c165f","index":"3","hash":"MWiNr"}]},"Prime Golem":{"hashedName":"taVxRU","checksum":"74PG","artworks":[{"id":"60b4cdd1-0eb4-42fa-9e84-240b001d2af7","index":"1","hash":"XGEuv"},{"id":"ffb1e104-375b-4f63-8128-521e20f32108","index":"3","hash":"LHzIc"},{"id":"cd68eca5-b2a0-4c1c-8754-be10ef5594c4","index":"2","hash":"QaFEL"},{"id":"cd68eca5-b2a0-4c1c-8754-be10ef5594c4","index":"0","hash":"XZCcN"},{"id":"2627db62-ac7f-48d3-8657-931ef0586217","index":"0","hash":"a+KAv"}]},"Siegebreaker":{"hashedName":"PCfwlD","checksum":"uHMW","artworks":[{"id":"9978fdf6-d358-4abc-9d71-d32a8d78e40a","index":"1","hash":"WqsRW"},{"id":"0e512ffb-8345-4946-84e7-5131a9bbf7ae","index":"2","hash":"VVumM"},{"id":"0e512ffb-8345-4946-84e7-5131a9bbf7ae","index":"0","hash":"yv1ZK"},{"id":"71ad0300-4ba1-428b-8822-b9eb4533ed5b","index":"2","hash":"5a4bF"},{"id":"f1e95a77-2ca1-473a-a951-6d24ac381780","index":"0","hash":"U11j1"},{"id":"f1e95a77-2ca1-473a-a951-6d24ac381780","index":"1","hash":"OquyT"}]},"Snow Crane":{"hashedName":"Aa1Ig4","checksum":"ClO4","artworks":[{"id":"f49f8020-8320-4fdc-ae76-8030c07ee2b5","index":"0","hash":"WX13k"},{"id":"7f3fc151-552c-4fdc-8562-e0fb8c45fd4e","index":"1","hash":"vv16x"},{"id":"2d0e2890-33fe-48d4-b23e-7e57b1b55461","index":"3","hash":"R7Imi"},{"id":"c4613f86-a57d-47d7-a262-96719837ce9c","index":"1","hash":"ZOgej"},{"id":"2d0e2890-33fe-48d4-b23e-7e57b1b55461","index":"2","hash":"Th2kU"}]},"Stormforged Recruit":{"hashedName":"aAGWfe","checksum":"KANV","artworks":[{"id":"1c4b3aa0-24ce-4b0d-932d-a4ef2357ffd3","index":"3","hash":"grmae"},{"id":"f7f3688f-3853-44d1-bca6-d995d6876cc0","index":"3","hash":"dF1EW"},{"id":"a7bc418c-0990-4a3f-bc7d-3afbdf436f51","index":"3","hash":"NfXWY"},{"id":"e18914ea-b88b-4850-b270-9a974e0f9c38","index":"3","hash":"ddUil"},{"id":"cad89887-2107-4a4a-a838-1f9e91e99c08","index":"3","hash":"ZWmiP"},{"id":"cad89887-2107-4a4a-a838-1f9e91e99c08","index":"0","hash":"EUzXk"},{"id":"4472fa6e-c6fb-4157-b854-c8e1d2b42995","index":"3","hash":"ymVkV"}]},"Supply Camel":{"hashedName":"BH5wUV","checksum":"BWKO","artworks":[{"id":"c9d4bd01-17d8-4d2f-9739-b9d56ab0d774","index":"2","hash":"TQnOa"},{"id":"c9d4bd01-17d8-4d2f-9739-b9d56ab0d774","index":"0","hash":"Pv/pk"},{"id":"1896af7e-08b8-4744-8b7a-ffb98cf9d3de","index":"1","hash":"ESdM/"},{"id":"6a68bc3e-bd7f-4880-954d-ff357e0580c0","index":"2","hash":"GQb7+"},{"id":"8300a565-8179-4b9c-9445-18cd11e30feb","index":"2","hash":"Vecj2"}]},"Trusty Companion":{"hashedName":"mhs3FM","checksum":"oONm","artworks":[{"id":"7953e818-8128-4a30-b696-521dc3af66e0","index":"2","hash":"a1r47"},{"id":"8eec2fb9-6cc5-4526-b1b2-63f80ac65f95","index":"1","hash":"nAh+h"}]},"Bloodfleet Raider":{"hashedName":"rO/K43","checksum":"GEqo","artworks":[{"id":"aa227e04-65dd-48c2-abfd-6e6fa6008da2","index":"0","hash":"nx2Ad"},{"id":"aa227e04-65dd-48c2-abfd-6e6fa6008da2","index":"3","hash":"Z9uO+"},{"id":"b4c3f4b0-05dc-4917-a882-3e522fb1d744","index":"3","hash":"haY2b"},{"id":"b4c3f4b0-05dc-4917-a882-3e522fb1d744","index":"1","hash":"hZlYa"},{"id":"af6bbace-c1a5-4a89-859d-e260f362a5a4","index":"2","hash":"7BCH2"},{"id":"18828197-cdfc-419a-ae08-acae2277df70","index":"1","hash":"Rj3Bv"},{"id":"18828197-cdfc-419a-ae08-acae2277df70","index":"0","hash":"i2F2F"}]},"Caring Mother":{"hashedName":"Hautnh","checksum":"8I4c","artworks":[{"id":"058ca6a3-cba6-4255-a098-e15d86ecc1d3","index":"3","hash":"qoBS7"},{"id":"a770b241-fcb3-4872-830b-d7c0ffd5ae73","index":"3","hash":"BCMSN"},{"id":"1702a29f-fe1f-40f0-aeb3-2892a3f1c0bc","index":"2","hash":"7p3Fz"}]},"Dojo Drill Instructor":{"hashedName":"H6gfbf","checksum":"Gp+H","artworks":[{"id":"ce889b3b-91f9-4ff2-add2-e60285c57b17","index":"1","hash":"vbaSQ"},{"id":"b2dbb6cd-e386-4a06-bf27-555adcb9d763","index":"2","hash":"Vtuhl"},{"id":"7de8364c-0f5a-4d7b-b841-1f453c148129","index":"0","hash":"WIS1v"}]},"Ironclad Jailwalker":{"hashedName":"RCgVt0","checksum":"27fW","artworks":[{"id":"8cc237fc-a571-4903-b553-94f9efeddb14","index":"1","hash":"z8F4Q"},{"id":"8cc237fc-a571-4903-b553-94f9efeddb14","index":"2","hash":"1a55Z"},{"id":"1ba85f4c-e36a-405c-84dd-450c9b836a2a","index":"0","hash":"naEvR"},{"id":"d8f42a0c-63c6-40cf-9275-6ffc2157f99f","index":"1","hash":"gv7bH"},{"id":"e6884d89-a8ec-43ec-85a8-dcc30ca69669","index":"3","hash":"nBuKm"}]},"Rampart Shellback":{"hashedName":"SaE/YR","checksum":"oPVz","artworks":[{"id":"beade48b-dfc3-4b0d-a7b3-e813a507b363","index":"0","hash":"M2LRx"},{"id":"aff786fd-7fc1-4a2d-9343-59060d86249f","index":"0","hash":"oPC18"},{"id":"3a69abc9-4dbb-4de3-8916-1f75f4991dac","index":"3","hash":"3cr7U"},{"id":"5c6c381c-6392-4f21-a9e1-c5126a4d283d","index":"2","hash":"0qflB"},{"id":"9782e556-bad6-4ad2-9833-8d831131a5eb","index":"1","hash":"XYcJD"},{"id":"939e6242-52c0-48ac-b399-3e52fec2a04a","index":"0","hash":"RvqN4"},{"id":"b1d61053-bd99-4609-9c8c-ba7d1af8873a","index":"2","hash":"UWsrs"},{"id":"cbeba22e-057c-463e-8a6c-d84fec4e4147","index":"0","hash":"OsPAb"}]},"Scalehide Trapper":{"hashedName":"NrZnSE","checksum":"Qb0m","artworks":[{"id":"2ba47d27-dbef-49be-8e14-890b895409a3","index":"2","hash":"9Pync"},{"id":"c6991389-b3bd-41f0-94f8-3a128fa5ced1","index":"3","hash":"eUTBD"},{"id":"5bd0ca22-a83a-414a-9139-c2092a485671","index":"1","hash":"aovzN"},{"id":"22a8f992-981f-46f6-9814-6acd4fd78883","index":"2","hash":"aT7wm"},{"id":"e9ced58e-d729-4c3b-b959-01736c8f312f","index":"1","hash":"SgNI+"},{"id":"a40c6919-d2e2-4cdd-a1de-4ce6a532def9","index":"3","hash":"Gj6qf"},{"id":"9d1c0ad9-d7ac-48b5-8887-39cdbcde27cd","index":"2","hash":"+R70G"},{"id":"08e98d57-c82d-41bf-974e-2594723e8387","index":"3","hash":"kb2Wd"},{"id":"8edd484f-1cb1-4f1f-933e-b6506442c848","index":"1","hash":"H5sIR"},{"id":"cd0955a7-8a85-43d7-97b8-c639bd21502c","index":"3","hash":"qWt+v"}]},"Trapmaster":{"hashedName":"NKUpWl","checksum":"L4I5","artworks":[{"id":"2a3b4bb4-107d-4a0e-82e5-32c1dc607528","index":"0","hash":"Lk4wl"},{"id":"1b7457f5-ab2d-4751-b1f3-3957be5a28c2","index":"2","hash":"WyuZz"},{"id":"d5d7a3d8-bc57-4d5e-9030-e092ef28934d","index":"1","hash":"K2QJL"},{"id":"d75ae876-16de-4a4f-80fb-098c3204e2e3","index":"2","hash":"towGS"},{"id":"834cdaa2-b2f5-4156-998e-506a5ca68984","index":"2","hash":"tg/J9"},{"id":"104896b4-1644-44c0-97cb-a115a5a27f3b","index":"0","hash":"Jz8rI"},{"id":"d04ef1e9-013f-4c58-8d1d-7d6410f55644","index":"3","hash":"Awcgj"},{"id":"b1a05e1b-d3e7-4c3b-8a21-e208cfcab472","index":"0","hash":"wphvp"},{"id":"32c69796-a1fc-4d40-86e1-8b215a05bb23","index":"0","hash":"0+AE8"}]},"Augur of the Moonspear":{"hashedName":"mnJ1rx","checksum":"Vj7K","artworks":[{"id":"f708086f-145d-4ad0-9476-e5c3de78f661","index":"3","hash":"Fz0Oh"},{"id":"ca45b97d-ac28-459d-8fb9-5efff2a635e4","index":"0","hash":"GRY9V"},{"id":"ca45b97d-ac28-459d-8fb9-5efff2a635e4","index":"1","hash":"o8/LV"},{"id":"aee22cf0-e1c9-45a5-a846-dba786d16a8c","index":"2","hash":"WrT5F"},{"id":"80b0da3a-75e9-4521-9a8a-d80a02376aef","index":"3","hash":"4H33S"},{"id":"6449d263-572c-48fd-abea-49b336ed533e","index":"0","hash":"Xk2kY"},{"id":"6aaaa00b-e42b-42c5-ba0e-45f3ec7aae7e","index":"2","hash":"Vde9x"},{"id":"6aaaa00b-e42b-42c5-ba0e-45f3ec7aae7e","index":"1","hash":"ws79k"}]},"Bloodfleet Harpooneer":{"hashedName":"yihw6E","checksum":"oUVb","artworks":[{"id":"51236e4b-aa09-40de-ae37-9c9b9cd7e7e5","index":"2","hash":"wAUE5"},{"id":"51236e4b-aa09-40de-ae37-9c9b9cd7e7e5","index":"0","hash":"0N9Xr"},{"id":"615b65df-6059-4623-9a52-ba6e23fd19a8","index":"3","hash":"YjQbX"},{"id":"615b65df-6059-4623-9a52-ba6e23fd19a8","index":"0","hash":"+qJ93"},{"id":"615b65df-6059-4623-9a52-ba6e23fd19a8","index":"1","hash":"LS7WO"}]},"Gold Colibri":{"hashedName":"uRFDUF","checksum":"9/cm","artworks":[{"id":"4b96f219-952d-4629-9ea5-07d8b6625b64","index":"3","hash":"+XSV/"},{"id":"9a06b103-b5a9-4d2f-a06c-f2a3692244cc","index":"0","hash":"KJsdV"},{"id":"b697235d-58dc-46a5-852e-9cf127307d53","index":"2","hash":"5C8Zl"},{"id":"fbd01acd-ec46-450e-a41b-df9c33a118ab","index":"1","hash":"pBUXR"}]},"Greedy Senator":{"hashedName":"FXoFE/","checksum":"s2HL","artworks":[{"id":"88e3f9b4-074b-4645-969f-b36b4a03b283","index":"0","hash":"kehZF"},{"id":"48ee5064-30f0-4f2f-bf04-ffa46a4af4b3","index":"2","hash":"RJ+Yq"},{"id":"1712423c-8247-4d89-938a-b7a8f72676d3","index":"3","hash":"4THcq"},{"id":"52110149-5889-41ad-8d65-2ed05aed8c38","index":"3","hash":"3DA/C"},{"id":"83be14db-adaf-4786-aeef-ad19b39bd2ca","index":"2","hash":"9kSs8"},{"id":"12fada4d-5aaf-4322-b3d3-24be5496e64d","index":"3","hash":"+Vzok"}]},"Paragon of Conquest":{"hashedName":"sD89NR","checksum":"1jBI","artworks":[{"id":"dc99fa2e-811a-4134-88e2-76ee3a711eec","index":"3","hash":"Rk/Ld"},{"id":"c4a83c37-4d6d-4f59-96bb-5d38ce1a9de6","index":"3","hash":"2DkTG"},{"id":"bdf467d6-4699-4676-a6f9-39e3cbb899e5","index":"0","hash":"Lo0b9"},{"id":"47bd8a99-96cc-4b41-bc50-6ab93ee3369d","index":"0","hash":"yKvkS"},{"id":"a1a13900-c801-42e6-af4f-64055214e78b","index":"2","hash":"yKoy5"},{"id":"26cf6a40-ae53-40b8-b6e8-cf911b9a91a6","index":"3","hash":"F6y/g"},{"id":"bb65025a-3646-4b47-89da-e109c9da39f9","index":"2","hash":"xF4f/"}]},"Tilling Yoke Beast":{"hashedName":"nCO2hV","checksum":"RyKb","artworks":[{"id":"1ee1739c-f460-4f92-977f-b926ed62b9c9","index":"2","hash":"4jB6S"},{"id":"210e4748-4c39-4d6d-84d6-16b05dcaab37","index":"1","hash":"Kwjmj"}]},"Ferromancer":{"hashedName":"q9jFp3","checksum":"HOeH","artworks":[{"id":"a407a34c-2a7a-47d2-858a-c385875cdc0c","index":"0","hash":"gUAjv"}]},"Frontier Centurion":{"hashedName":"ZsaD9G","checksum":"RvzK","artworks":[{"id":"e9cfddb2-74e8-4821-93ef-db5a57e9c0e6","index":"1","hash":"GQHji"},{"id":"3bf3147f-0874-4e69-a5cf-babf4744fc51","index":"3","hash":"nLf/g"},{"id":"37b0498c-4b19-4c10-b0ef-756203163b3f","index":"2","hash":"DbKL2"},{"id":"7f83f9df-7679-4c80-af2f-aaa0f9a41c1e","index":"0","hash":"qXdCW"},{"id":"b4e6f87d-bee5-4e2c-bc71-25002b90cf7b","index":"3","hash":"o80fG"},{"id":"b4e6f87d-bee5-4e2c-bc71-25002b90cf7b","index":"2","hash":"H0bhP"},{"id":"22a34a29-1762-4b99-a1b7-f4960f0961b3","index":"0","hash":"NAtrD"}]},"Cinderguard Saboteur":{"hashedName":"guMM7M","checksum":"2QjS","artworks":[{"id":"82cf010f-86e1-4c76-bba4-1f5a5c122086","index":"2","hash":"qnkL3"},{"id":"82cf010f-86e1-4c76-bba4-1f5a5c122086","index":"3","hash":"KRuDS"},{"id":"2be582e5-299d-470b-9cbc-a89027a4991d","index":"3","hash":"JTKwT"},{"id":"a3f9b0a5-cf95-46d6-b2ad-b875e23a9b7b","index":"3","hash":"rN6/T"},{"id":"a3f9b0a5-cf95-46d6-b2ad-b875e23a9b7b","index":"2","hash":"CLrjb"},{"id":"a3f9b0a5-cf95-46d6-b2ad-b875e23a9b7b","index":"1","hash":"SMaZT"},{"id":"b446efd1-d0f0-46e6-bb05-0789f08d931d","index":"1","hash":"hOcbX"},{"id":"b446efd1-d0f0-46e6-bb05-0789f08d931d","index":"3","hash":"lMKfI"},{"id":"74ae0134-7c5f-4b5f-b25f-6d6412423dc0","index":"1","hash":"4HW/D"}]},"Sandsilk Fox":{"hashedName":"cGGi0k","checksum":"Cx6a","artworks":[{"id":"d32d623f-8304-4652-a723-5e08c4834598","index":"1","hash":"JBlAe"},{"id":"d32d623f-8304-4652-a723-5e08c4834598","index":"0","hash":"L7EGu"}]},"Cryptroach":{"hashedName":"ttwPpj","checksum":"W7Oh","artworks":[{"id":"b6b028b1-6920-4dde-9694-73d589c7969e","index":"1","hash":"E8gNj"}]},"Shiverskull":{"hashedName":"hsw+J5","checksum":"bOwp","artworks":[{"id":"5531e7cf-23f3-4725-986f-2de126d022b2","index":"2","hash":"RfkeX"}]}}